ciphelpers/__init__.py
ciphelpers/error_handling_helper_functions.py
ciphelpers/general_helper_functions.py
ciphelpers/testing_helper_functions.py
ciphelpers/validation_helper_functions.py
ciphelpers-1.0.0.dist-info/METADATA
ciphelpers-1.0.0.dist-info/RECORD
ciphelpers-1.0.0.dist-info/WHEEL
ciphelpers-1.0.0.dist-info/top_level.txt
